streamsx/wml/__init__.py
streamsx/wml/_wml.py
streamsx/wml/utils.py
streamsx/wml/bundleresthandler/__init__.py
streamsx/wml/bundleresthandler/bundlecontroller.py
streamsx/wml/bundleresthandler/bundleresthandler.py
streamsx/wml/bundleresthandler/wmlbundlecontroller.py
streamsx/wml/bundleresthandler/wmlbundleresthandler.py
streamsx/wml/spl/toolkit.wml/com.ibm.streams.wml/info.xml
streamsx/wml/spl/toolkit.wml/com.ibm.streams.wml/opt/python/streams/requirements.txt
streamsx/wml/spl/toolkit.wml/com.ibm.streams.wml/opt/python/streams/wml_online_scoring.py
streamsx/wml/spl/toolkit.wml/com.ibm.streams.wml/opt/python/streams/bundleresthandler/bundlecontroller.py
streamsx/wml/spl/toolkit.wml/com.ibm.streams.wml/opt/python/streams/bundleresthandler/bundleresthandler.py
streamsx/wml/spl/toolkit.wml/com.ibm.streams.wml/opt/python/streams/bundleresthandler/wmlbundlecontroller.py
streamsx/wml/spl/toolkit.wml/com.ibm.streams.wml/opt/python/streams/bundleresthandler/wmlbundleresthandler.py
streamsx.wml-1.1.0.dist-info/LICENSE.txt
streamsx.wml-1.1.0.dist-info/METADATA
streamsx.wml-1.1.0.dist-info/WHEEL
streamsx.wml-1.1.0.dist-info/top_level.txt
streamsx.wml-1.1.0.dist-info/RECORD
