Metadata-Version: 2.1
Name: streamsx.wml
Version: 1.1.0
Summary: Watson Machine Learning online scoring integration in IBM Streams topology applications
Home-page: https://github.com/IBMStreams/pypi.streamsx.wml
Author: IBM Streams @ github.com
Author-email: hegermar@de.ibm.com
License: Apache License - Version 2.0
Keywords: streams,ibmstreams,streaming,analytics,streaming-analytics,wml,streamsx,topology
Platform: UNKNOWN
Classifier: Development Status :: 4 - Beta
Classifier: License :: OSI Approved :: Apache Software License
Classifier: Programming Language :: Python :: 3
Classifier: Programming Language :: Python :: 3.5
Classifier: Programming Language :: Python :: 3.6
Classifier: Programming Language :: Python :: 3.7
Requires-Dist: streamsx (>=1.13.15)
